[
  {
    "ts": "2026-07-11T16:05:08.573Z",
    "symbol": "ETCUSDT",
    "signal": "SHORT",
    "confidence": 79,
    "reason": "above VWAP 0.22%→SHORT | ask-heavy(38%)→SHORT",
    "price": 7.096,
    "mode": "live",
    "order_id": 515943867,
    "order_qty": "35.23"
  },
  {
    "ts": "2026-07-11T16:05:08.618Z",
    "symbol": "DOGEUSDT",
    "signal": "SHORT",
    "confidence": 91,
    "reason": "StochRSI overbought-turn(94.6/98.2)→SHORT | above VWAP 2.49%→SHORT | ask-heavy(43%)→SHORT",
    "price": 0.07519,
    "mode": "live",
    "error": "Request failed with status code 400"
  },
  {
    "ts": "2026-07-11T16:05:08.664Z",
    "symbol": "OPUSDT",
    "signal": "SHORT",
    "confidence": 79,
    "reason": "above VWAP 1.92%→SHORT | ask-heavy(37%)→SHORT",
    "price": 0.1065,
    "mode": "live",
    "error": "Request failed with status code 400"
  },
  {
    "ts": "2026-07-11T16:05:08.707Z",
    "symbol": "OPUSDT",
    "signal": "SHORT",
    "confidence": 79,
    "reason": "above VWAP 3.34%→SHORT | ask-heavy(37%)→SHORT",
    "price": 0.1065,
    "mode": "live",
    "error": "Request failed with status code 400"
  },
  {
    "ts": "2026-07-11T16:05:08.606Z",
    "symbol": "ETCUSDT",
    "signal": "SHORT",
    "confidence": 79,
    "reason": "above VWAP 1.52%→SHORT | ask-heavy(38%)→SHORT",
    "price": 7.096,
    "mode": "live",
    "order_id": 515943870,
    "order_qty": "14.09"
  },
  {
    "ts": "2026-07-11T16:05:08.633Z",
    "symbol": "LINKUSDT",
    "signal": "SHORT",
    "confidence": 79,
    "reason": "StochRSI overbought-turn(91.8/97)→SHORT | above VWAP 3.07%→SHORT",
    "price": 8.048,
    "mode": "live",
    "order_id": 806272557,
    "order_qty": "12.43"
  },
  {
    "ts": "2026-07-11T16:05:08.802Z",
    "symbol": "SOLUSDT",
    "signal": "SHORT",
    "confidence": 79,
    "reason": "above VWAP 0.77%→SHORT | ask-heavy(30%)→SHORT",
    "price": 78.3,
    "mode": "live",
    "order_id": 3055338235,
    "order_qty": "0.90"
  },
  {
    "ts": "2026-07-11T16:05:08.825Z",
    "symbol": "XLMUSDT",
    "signal": "SHORT",
    "confidence": 79,
    "reason": "above VWAP 2.27%→SHORT | ask-heavy(16%)→SHORT",
    "price": 0.19154,
    "mode": "live",
    "error": "Request failed with status code 400"
  },
  {
    "ts": "2026-07-11T16:05:08.858Z",
    "symbol": "XLMUSDT",
    "signal": "SHORT",
    "confidence": 79,
    "reason": "above VWAP 0.59%→SHORT | ask-heavy(16%)→SHORT",
    "price": 0.19154,
    "mode": "live",
    "error": "Request failed with status code 400"
  },
  {
    "ts": "2026-07-11T16:05:08.852Z",
    "symbol": "OPUSDT",
    "signal": "SHORT",
    "confidence": 79,
    "reason": "above VWAP 3.68%→SHORT | ask-heavy(37%)→SHORT",
    "price": 0.1065,
    "mode": "live",
    "error": "Request failed with status code 400"
  },
  {
    "ts": "2026-07-11T16:05:08.926Z",
    "symbol": "HBARUSDT",
    "signal": "SHORT",
    "confidence": 79,
    "reason": "StochRSI overbought-turn(87.7/95.4)→SHORT | ask-heavy(33%)→SHORT",
    "price": 0.06951,
    "mode": "live",
    "error": "Request failed with status code 400"
  },
  {
    "ts": "2026-07-11T16:05:09.005Z",
    "symbol": "ALGOUSDT",
    "signal": "SHORT",
    "confidence": 79,
    "reason": "above VWAP 0.55%→SHORT | VOL SPIKE 1.9x | ask-heavy(40%)→SHORT",
    "price": 0.0866,
    "mode": "live",
    "error": "Request failed with status code 400"
  },
  {
    "ts": "2026-07-11T16:05:09.007Z",
    "symbol": "ALGOUSDT",
    "signal": "SHORT",
    "confidence": 91,
    "reason": "StochRSI overbought-turn(75.7/88.4)→SHORT | above VWAP 1.32%→SHORT | ask-heavy(40%)→SHORT",
    "price": 0.0866,
    "mode": "live",
    "error": "Request failed with status code 400"
  },
  {
    "ts": "2026-07-11T16:05:08.833Z",
    "symbol": "LTCUSDT",
    "signal": "SHORT",
    "confidence": 91,
    "reason": "StochRSI overbought-turn(96.7/98.5)→SHORT | above VWAP 3.54%→SHORT | ask-heavy(40%)→SHORT",
    "price": 45.03,
    "mode": "live",
    "order_id": 1310250252,
    "order_qty": "1.480"
  },
  {
    "ts": "2026-07-11T16:05:08.853Z",
    "symbol": "LTCUSDT",
    "signal": "SHORT",
    "confidence": 79,
    "reason": "above VWAP 0.38%→SHORT | ask-heavy(40%)→SHORT",
    "price": 45.03,
    "mode": "live",
    "order_id": 1310250254,
    "order_qty": "5.550"
  },
  {
    "ts": "2026-07-11T16:05:09.070Z",
    "symbol": "XRPUSDT",
    "signal": "SHORT",
    "confidence": 79,
    "reason": "above VWAP 2.81%→SHORT | ask-heavy(41%)→SHORT",
    "price": 1.1118,
    "mode": "live",
    "error": "Request failed with status code 400"
  },
  {
    "ts": "2026-07-11T16:05:09.048Z",
    "symbol": "XRPUSDT",
    "signal": "SHORT",
    "confidence": 79,
    "reason": "above VWAP 0.54%→SHORT | ask-heavy(41%)→SHORT",
    "price": 1.1118,
    "mode": "live",
    "error": "Request failed with status code 400"
  },
  {
    "ts": "2026-07-11T16:05:08.832Z",
    "symbol": "LTCUSDT",
    "signal": "SHORT",
    "confidence": 79,
    "reason": "above VWAP 2.11%→SHORT | ask-heavy(40%)→SHORT",
    "price": 45.03,
    "mode": "live",
    "order_id": 1310250256,
    "order_qty": "2.220"
  },
  {
    "ts": "2026-07-11T16:05:09.169Z",
    "symbol": "ADAUSDT",
    "signal": "SHORT",
    "confidence": 79,
    "reason": "StochRSI overbought-turn(86.5/93.5)→SHORT | above VWAP 2.29%→SHORT",
    "price": 0.1716,
    "mode": "live",
    "error": "Request failed with status code 400"
  },
  {
    "ts": "2026-07-11T16:05:09.202Z",
    "symbol": "XRPUSDT",
    "signal": "SHORT",
    "confidence": 91,
    "reason": "StochRSI overbought-turn(89.3/95)→SHORT | above VWAP 1.09%→SHORT | ask-heavy(41%)→SHORT",
    "price": 1.1118,
    "mode": "live",
    "error": "Request failed with status code 400"
  },
  {
    "ts": "2026-07-11T16:05:09.243Z",
    "symbol": "ADAUSDT",
    "signal": "SHORT",
    "confidence": 79,
    "reason": "StochRSI overbought-turn(99/99.7)→SHORT | above VWAP 1.74%→SHORT",
    "price": 0.1716,
    "mode": "live",
    "error": "Request failed with status code 400"
  },
  {
    "ts": "2026-07-11T16:05:10.005Z",
    "symbol": "APTUSDT",
    "signal": "SHORT",
    "confidence": 79,
    "reason": "above VWAP 1.06%→SHORT | ask-heavy(35%)→SHORT",
    "price": 0.638,
    "mode": "live",
    "error": "Request failed with status code 400"
  },
  {
    "ts": "2026-07-11T16:05:10.008Z",
    "symbol": "APTUSDT",
    "signal": "SHORT",
    "confidence": 79,
    "reason": "above VWAP 4.02%→SHORT | ask-heavy(35%)→SHORT",
    "price": 0.638,
    "mode": "live",
    "error": "Request failed with status code 400"
  },
  {
    "ts": "2026-07-11T16:05:10.005Z",
    "symbol": "APTUSDT",
    "signal": "SHORT",
    "confidence": 79,
    "reason": "above VWAP 1.92%→SHORT | ask-heavy(35%)→SHORT",
    "price": 0.638,
    "mode": "live",
    "error": "Request failed with status code 400"
  },
  {
    "ts": "2026-07-11T16:05:15.267Z",
    "symbol": "BCHUSDT",
    "signal": "SHORT",
    "confidence": 79,
    "reason": "above VWAP 0.70%→SHORT | ask-heavy(34%)→SHORT",
    "price": 248.09,
    "mode": "live",
    "order_id": 1929872920,
    "order_qty": "1.010"
  },
  {
    "ts": "2026-07-11T16:05:15.296Z",
    "symbol": "BCHUSDT",
    "signal": "SHORT",
    "confidence": 79,
    "reason": "above VWAP 14.52%→SHORT | ask-heavy(34%)→SHORT",
    "price": 248.09,
    "mode": "live",
    "order_id": 1929872926,
    "order_qty": "0.270"
  },
  {
    "ts": "2026-07-11T16:05:15.335Z",
    "symbol": "BCHUSDT",
    "signal": "SHORT",
    "confidence": 91,
    "reason": "StochRSI overbought-turn(78.1/89)→SHORT | above VWAP 3.25%→SHORT | ask-heavy(34%)→SHORT",
    "price": 248.09,
    "mode": "live",
    "order_id": 1929872932,
    "order_qty": "0.400"
  },
  {
    "ts": "2026-07-11T16:05:38.498Z",
    "symbol": "INJUSDT",
    "signal": "LONG",
    "confidence": 79,
    "reason": "below VWAP -0.30%→LONG | VOL SPIKE 5.2x | bid-heavy(57%)→LONG",
    "price": 4.989,
    "mode": "live",
    "error": "Request failed with status code 400"
  },
  {
    "ts": "2026-07-11T16:05:38.842Z",
    "symbol": "ARBUSDT",
    "signal": "SHORT",
    "confidence": 79,
    "reason": "above VWAP 6.51%→SHORT | ask-heavy(34%)→SHORT",
    "price": 0.099,
    "mode": "live",
    "error": "Request failed with status code 400"
  },
  {
    "ts": "2026-07-11T16:05:40.038Z",
    "symbol": "OPUSDT",
    "signal": "SHORT",
    "confidence": 79,
    "reason": "above VWAP 1.83%→SHORT | ask-heavy(37%)→SHORT",
    "price": 0.1064,
    "mode": "live",
    "error": "Request failed with status code 400"
  },
  {
    "ts": "2026-07-11T16:05:40.082Z",
    "symbol": "XLMUSDT",
    "signal": "SHORT",
    "confidence": 79,
    "reason": "above VWAP 0.58%→SHORT | ask-heavy(17%)→SHORT",
    "price": 0.19152,
    "mode": "live",
    "error": "Request failed with status code 400"
  },
  {
    "ts": "2026-07-11T16:05:40.922Z",
    "symbol": "APTUSDT",
    "signal": "SHORT",
    "confidence": 79,
    "reason": "above VWAP 0.94%→SHORT | ask-heavy(39%)→SHORT",
    "price": 0.6372,
    "mode": "live",
    "error": "Request failed with status code 400"
  },
  {
    "ts": "2026-07-11T16:06:10.348Z",
    "symbol": "ARBUSDT",
    "signal": "SHORT",
    "confidence": 79,
    "reason": "above VWAP 6.51%→SHORT | ask-heavy(37%)→SHORT",
    "price": 0.099,
    "mode": "live",
    "error": "Request failed with status code 400"
  },
  {
    "ts": "2026-07-11T16:06:11.027Z",
    "symbol": "APTUSDT",
    "signal": "SHORT",
    "confidence": 79,
    "reason": "above VWAP 0.82%→SHORT | ask-heavy(41%)→SHORT",
    "price": 0.6365,
    "mode": "live",
    "error": "Request failed with status code 400"
  },
  {
    "ts": "2026-07-11T16:06:11.083Z",
    "symbol": "OPUSDT",
    "signal": "SHORT",
    "confidence": 79,
    "reason": "above VWAP 1.83%→SHORT | ask-heavy(37%)→SHORT",
    "price": 0.1064,
    "mode": "live",
    "error": "Request failed with status code 400"
  },
  {
    "ts": "2026-07-11T16:06:11.463Z",
    "symbol": "XLMUSDT",
    "signal": "SHORT",
    "confidence": 79,
    "reason": "above VWAP 0.54%→SHORT | ask-heavy(24%)→SHORT",
    "price": 0.19144,
    "mode": "live",
    "error": "Request failed with status code 400"
  },
  {
    "ts": "2026-07-11T16:06:41.188Z",
    "symbol": "ARBUSDT",
    "signal": "SHORT",
    "confidence": 79,
    "reason": "above VWAP 6.19%→SHORT | ask-heavy(41%)→SHORT",
    "price": 0.0987,
    "mode": "live",
    "error": "Request failed with status code 400"
  },
  {
    "ts": "2026-07-11T16:06:41.554Z",
    "symbol": "XLMUSDT",
    "signal": "SHORT",
    "confidence": 79,
    "reason": "above VWAP 0.52%→SHORT | ask-heavy(36%)→SHORT",
    "price": 0.1914,
    "mode": "live",
    "error": "Request failed with status code 400"
  },
  {
    "ts": "2026-07-11T16:06:42.174Z",
    "symbol": "APTUSDT",
    "signal": "SHORT",
    "confidence": 79,
    "reason": "above VWAP 0.94%→SHORT | ask-heavy(41%)→SHORT",
    "price": 0.6372,
    "mode": "live",
    "error": "Request failed with status code 400"
  },
  {
    "ts": "2026-07-11T16:07:11.588Z",
    "symbol": "ARBUSDT",
    "signal": "SHORT",
    "confidence": 79,
    "reason": "above VWAP 6.19%→SHORT | ask-heavy(40%)→SHORT",
    "price": 0.0987,
    "mode": "live",
    "order_id": 234316906,
    "order_qty": "2535.5"
  },
  {
    "ts": "2026-07-11T16:07:11.832Z",
    "symbol": "XLMUSDT",
    "signal": "SHORT",
    "confidence": 79,
    "reason": "above VWAP 0.54%→SHORT | ask-heavy(31%)→SHORT",
    "price": 0.19145,
    "mode": "live",
    "error": "Request failed with status code 400"
  },
  {
    "ts": "2026-07-11T16:07:12.556Z",
    "symbol": "APTUSDT",
    "signal": "SHORT",
    "confidence": 79,
    "reason": "above VWAP 1.05%→SHORT | ask-heavy(41%)→SHORT",
    "price": 0.6379,
    "mode": "live",
    "error": "Request failed with status code 400"
  },
  {
    "ts": "2026-07-11T16:07:42.726Z",
    "symbol": "APTUSDT",
    "signal": "SHORT",
    "confidence": 79,
    "reason": "above VWAP 1.00%→SHORT | ask-heavy(41%)→SHORT",
    "price": 0.6376,
    "mode": "live",
    "error": "Request failed with status code 400"
  },
  {
    "ts": "2026-07-11T16:09:13.492Z",
    "symbol": "ARBUSDT",
    "signal": "SHORT",
    "confidence": 79,
    "reason": "above VWAP 5.67%→SHORT | ask-heavy(33%)→SHORT",
    "price": 0.0982,
    "mode": "live",
    "error": "Request failed with status code 400"
  },
  {
    "ts": "2026-07-11T16:09:43.667Z",
    "symbol": "ARBUSDT",
    "signal": "SHORT",
    "confidence": 79,
    "reason": "above VWAP 5.46%→SHORT | ask-heavy(35%)→SHORT",
    "price": 0.098,
    "mode": "live",
    "error": "Request failed with status code 400"
  },
  {
    "ts": "2026-07-11T16:10:08.634Z",
    "symbol": "SUIUSDT",
    "signal": "SHORT",
    "confidence": 91,
    "reason": "StochRSI overbought-turn(89.5/94.5)→SHORT | above VWAP 1.57%→SHORT | ask-heavy(39%)→SHORT",
    "price": 0.7404,
    "mode": "live",
    "error": "Request failed with status code 400"
  },
  {
    "ts": "2026-07-11T16:10:08.774Z",
    "symbol": "AVAXUSDT",
    "signal": "SHORT",
    "confidence": 79,
    "reason": "StochRSI overbought-turn(91.8/97.3)→SHORT | above VWAP 1.76%→SHORT",
    "price": 6.738,
    "mode": "live",
    "error": "Request failed with status code 400"
  },
  {
    "ts": "2026-07-11T16:10:08.936Z",
    "symbol": "TIAUSDT",
    "signal": "SHORT",
    "confidence": 79,
    "reason": "StochRSI overbought-turn(83.5/91.4)→SHORT | above VWAP 3.70%→SHORT",
    "price": 0.414,
    "mode": "live",
    "error": "Request failed with status code 400"
  },
  {
    "ts": "2026-07-11T16:10:08.957Z",
    "symbol": "UNIUSDT",
    "signal": "SHORT",
    "confidence": 79,
    "reason": "StochRSI overbought-turn(88.7/92.2)→SHORT | above VWAP 10.27%→SHORT",
    "price": 3.731,
    "mode": "live",
    "error": "Request failed with status code 400"
  },
  {
    "ts": "2026-07-11T16:10:09.031Z",
    "symbol": "DOGEUSDT",
    "signal": "SHORT",
    "confidence": 79,
    "reason": "StochRSI overbought-turn(96.8/98.1)→SHORT | above VWAP 1.17%→SHORT",
    "price": 0.0751,
    "mode": "live",
    "error": "Request failed with status code 400"
  },
  {
    "ts": "2026-07-11T16:10:09.095Z",
    "symbol": "DOGEUSDT",
    "signal": "SHORT",
    "confidence": 79,
    "reason": "StochRSI overbought-turn(90.1/96.7)→SHORT | above VWAP 2.37%→SHORT",
    "price": 0.0751,
    "mode": "live",
    "error": "Request failed with status code 400"
  },
  {
    "ts": "2026-07-11T16:10:09.234Z",
    "symbol": "ALGOUSDT",
    "signal": "SHORT",
    "confidence": 79,
    "reason": "StochRSI overbought-turn(75.7/88.4)→SHORT | above VWAP 1.32%→SHORT",
    "price": 0.0866,
    "mode": "live",
    "error": "Request failed with status code 400"
  },
  {
    "ts": "2026-07-11T16:10:09.368Z",
    "symbol": "XRPUSDT",
    "signal": "SHORT",
    "confidence": 79,
    "reason": "StochRSI overbought-turn(84.5/93.4)→SHORT | above VWAP 1.02%→SHORT",
    "price": 1.111,
    "mode": "live",
    "error": "Request failed with status code 400"
  },
  {
    "ts": "2026-07-11T16:10:09.549Z",
    "symbol": "ARBUSDT",
    "signal": "SHORT",
    "confidence": 79,
    "reason": "above VWAP 13.21%→SHORT | ask-heavy(42%)→SHORT",
    "price": 0.0981,
    "mode": "live",
    "error": "Request failed with status code 400"
  },
  {
    "ts": "2026-07-11T16:10:09.545Z",
    "symbol": "LINKUSDT",
    "signal": "SHORT",
    "confidence": 79,
    "reason": "StochRSI overbought-turn(84.3/94.5)→SHORT | above VWAP 2.93%→SHORT",
    "price": 8.037,
    "mode": "live",
    "order_id": 806296691,
    "order_qty": "12.44"
  },
  {
    "ts": "2026-07-11T16:10:09.686Z",
    "symbol": "LTCUSDT",
    "signal": "SHORT",
    "confidence": 79,
    "reason": "StochRSI overbought-turn(98.1/99)→SHORT | above VWAP 3.60%→SHORT",
    "price": 45.06,
    "mode": "live",
    "order_id": 1310282709,
    "order_qty": "1.480"
  },
  {
    "ts": "2026-07-11T16:10:10.303Z",
    "symbol": "APTUSDT",
    "signal": "SHORT",
    "confidence": 79,
    "reason": "above VWAP 3.97%→SHORT | ask-heavy(38%)→SHORT",
    "price": 0.6377,
    "mode": "live",
    "error": "Request failed with status code 400"
  },
  {
    "ts": "2026-07-11T16:10:10.303Z",
    "symbol": "APTUSDT",
    "signal": "SHORT",
    "confidence": 79,
    "reason": "above VWAP 1.88%→SHORT | ask-heavy(37%)→SHORT",
    "price": 0.6377,
    "mode": "live",
    "error": "Request failed with status code 400"
  },
  {
    "ts": "2026-07-11T16:10:10.731Z",
    "symbol": "OPUSDT",
    "signal": "SHORT",
    "confidence": 79,
    "reason": "above VWAP 3.19%→SHORT | ask-heavy(27%)→SHORT",
    "price": 0.106,
    "mode": "live",
    "error": "Request failed with status code 400"
  },
  {
    "ts": "2026-07-11T16:10:10.731Z",
    "symbol": "OPUSDT",
    "signal": "SHORT",
    "confidence": 79,
    "reason": "above VWAP 2.85%→SHORT | ask-heavy(27%)→SHORT",
    "price": 0.106,
    "mode": "live",
    "error": "Request failed with status code 400"
  },
  {
    "ts": "2026-07-11T16:10:14.995Z",
    "symbol": "ARBUSDT",
    "signal": "SHORT",
    "confidence": 79,
    "reason": "above VWAP 5.56%→SHORT | ask-heavy(43%)→SHORT",
    "price": 0.0981,
    "mode": "live",
    "error": "Request failed with status code 400"
  },
  {
    "ts": "2026-07-11T16:10:16.013Z",
    "symbol": "BCHUSDT",
    "signal": "SHORT",
    "confidence": 79,
    "reason": "above VWAP 0.54%→SHORT | ask-heavy(33%)→SHORT",
    "price": 247.71,
    "mode": "live",
    "order_id": 1929945888,
    "order_qty": "1.010"
  },
  {
    "ts": "2026-07-11T16:10:16.545Z",
    "symbol": "BCHUSDT",
    "signal": "SHORT",
    "confidence": 79,
    "reason": "above VWAP 14.33%→SHORT | ask-heavy(33%)→SHORT",
    "price": 247.67,
    "mode": "live",
    "order_id": 1929946009,
    "order_qty": "0.270"
  },
  {
    "ts": "2026-07-11T16:10:16.554Z",
    "symbol": "BCHUSDT",
    "signal": "SHORT",
    "confidence": 79,
    "reason": "above VWAP 3.08%→SHORT | ask-heavy(33%)→SHORT",
    "price": 247.67,
    "mode": "live",
    "order_id": 1929946010,
    "order_qty": "0.400"
  },
  {
    "ts": "2026-07-11T16:15:09.904Z",
    "symbol": "AVAXUSDT",
    "signal": "SHORT",
    "confidence": 91,
    "reason": "StochRSI overbought-turn(99.2/99.7)→SHORT | above VWAP 1.91%→SHORT | ask-heavy(28%)→SHORT",
    "price": 6.748,
    "mode": "live",
    "error": "Request failed with status code 400"
  },
  {
    "ts": "2026-07-11T16:15:09.899Z",
    "symbol": "SUIUSDT",
    "signal": "SHORT",
    "confidence": 91,
    "reason": "StochRSI overbought-turn(92.6/95.5)→SHORT | above VWAP 1.79%→SHORT | ask-heavy(17%)→SHORT",
    "price": 0.742,
    "mode": "live",
    "error": "Request failed with status code 400"
  },
  {
    "ts": "2026-07-11T16:15:10.076Z",
    "symbol": "TIAUSDT",
    "signal": "SHORT",
    "confidence": 79,
    "reason": "StochRSI overbought-turn(87.4/92.7)→SHORT | above VWAP 4.05%→SHORT",
    "price": 0.4154,
    "mode": "live",
    "error": "Request failed with status code 400"
  },
  {
    "ts": "2026-07-11T16:15:10.111Z",
    "symbol": "UNIUSDT",
    "signal": "SHORT",
    "confidence": 79,
    "reason": "StochRSI overbought-turn(91.1/93)→SHORT | above VWAP 10.60%→SHORT",
    "price": 3.742,
    "mode": "live",
    "error": "Request failed with status code 400"
  },
  {
    "ts": "2026-07-11T16:15:10.416Z",
    "symbol": "DOGEUSDT",
    "signal": "SHORT",
    "confidence": 91,
    "reason": "StochRSI overbought-turn(98.9/99.6)→SHORT | above VWAP 2.60%→SHORT | ask-heavy(38%)→SHORT",
    "price": 0.07527,
    "mode": "live",
    "error": "Request failed with status code 400"
  },
  {
    "ts": "2026-07-11T16:15:10.413Z",
    "symbol": "DOGEUSDT",
    "signal": "SHORT",
    "confidence": 79,
    "reason": "above VWAP 1.40%→SHORT | ask-heavy(38%)→SHORT",
    "price": 0.07527,
    "mode": "live",
    "error": "Request failed with status code 400"
  },
  {
    "ts": "2026-07-11T16:15:10.373Z",
    "symbol": "LINKUSDT",
    "signal": "SHORT",
    "confidence": 91,
    "reason": "StochRSI overbought-turn(96.2/98.5)→SHORT | above VWAP 3.15%→SHORT | ask-heavy(29%)→SHORT",
    "price": 8.054,
    "mode": "live",
    "order_id": 806321018,
    "order_qty": "12.42"
  },
  {
    "ts": "2026-07-11T16:15:10.494Z",
    "symbol": "ALGOUSDT",
    "signal": "SHORT",
    "confidence": 79,
    "reason": "StochRSI overbought-turn(75.7/88.4)→SHORT | above VWAP 1.32%→SHORT",
    "price": 0.0866,
    "mode": "live",
    "order_id": 315698521,
    "order_qty": "1153.4"
  },
  {
    "ts": "2026-07-11T16:15:10.638Z",
    "symbol": "XRPUSDT",
    "signal": "SHORT",
    "confidence": 91,
    "reason": "StochRSI overbought-turn(92.4/96)→SHORT | above VWAP 1.14%→SHORT | ask-heavy(39%)→SHORT",
    "price": 1.1123,
    "mode": "live",
    "order_id": 2551086809,
    "order_qty": "89.9"
  },
  {
    "ts": "2026-07-11T16:15:11.124Z",
    "symbol": "APTUSDT",
    "signal": "SHORT",
    "confidence": 91,
    "reason": "StochRSI overbought-turn(76.2/88.1)→SHORT | above VWAP 1.99%→SHORT | ask-heavy(34%)→SHORT",
    "price": 0.6384,
    "mode": "live",
    "error": "Request failed with status code 400"
  },
  {
    "ts": "2026-07-11T16:15:11.568Z",
    "symbol": "OPUSDT",
    "signal": "SHORT",
    "confidence": 79,
    "reason": "above VWAP 3.24%→SHORT | ask-heavy(34%)→SHORT",
    "price": 0.1064,
    "mode": "live",
    "error": "Request failed with status code 400"
  },
  {
    "ts": "2026-07-11T16:15:11.572Z",
    "symbol": "OPUSDT",
    "signal": "SHORT",
    "confidence": 79,
    "reason": "above VWAP 3.58%→SHORT | ask-heavy(34%)→SHORT",
    "price": 0.1064,
    "mode": "live",
    "error": "Request failed with status code 400"
  },
  {
    "ts": "2026-07-11T16:15:17.290Z",
    "symbol": "BCHUSDT",
    "signal": "SHORT",
    "confidence": 79,
    "reason": "above VWAP 14.57%→SHORT | ask-heavy(32%)→SHORT",
    "price": 248.19,
    "mode": "live",
    "order_id": 1930019119,
    "order_qty": "0.270"
  },
  {
    "ts": "2026-07-11T16:15:17.286Z",
    "symbol": "BCHUSDT",
    "signal": "SHORT",
    "confidence": 91,
    "reason": "StochRSI overbought-turn(78.7/89.2)→SHORT | above VWAP 3.29%→SHORT | ask-heavy(32%)→SHORT",
    "price": 248.19,
    "mode": "live",
    "order_id": 1930019118,
    "order_qty": "0.400"
  }
]